miniBenchmark/FFT_power_spectral.py
miniBenchmark/Forests.py
miniBenchmark/PDE_BVP.py
miniBenchmark/__init__.py
miniBenchmark/benchmark_machine.py
miniBenchmark/detect_availability.py
miniBenchmark/detect_torch_availability.py
miniBenchmark/generate_data_tasks.py
miniBenchmark/invert_matrix.py
miniBenchmark/malloc.py
miniBenchmark/tab_dae.py
miniBenchmark/upscale_task.py
minibenchmark-0.0.1.dist-info/METADATA
minibenchmark-0.0.1.dist-info/WHEEL
minibenchmark-0.0.1.dist-info/RECORD
