Metadata-Version: 2.1
Name: miniBenchmark
Version: 0.0.1
Summary: Minimalistic benchmarking of computers with general data/ modeling and simulation purposes
Project-URL: Homepage, https://github.com/HaoLi111/miniBenchmark
Project-URL: Bug Tracker, https://github.com/HaoLi111/miniBenchmark/issues
Author-email: Hao LI <author@example.com>
Classifier: License :: OSI Approved :: MIT License
Classifier: Operating System :: OS Independent
Classifier: Programming Language :: Python :: 3
Requires-Python: >=3.7
